setup.cfg
setup.py
targeter/__init__.py
targeter/targeter.py
targeter.egg-info/PKG-INFO
targeter.egg-info/SOURCES.txt
targeter.egg-info/dependency_links.txt
targeter.egg-info/entry_points.txt
targeter.egg-info/not-zip-safe
targeter.egg-info/requires.txt
targeter.egg-info/top_level.txt