Metadata-Version: 1.0
Name: targeter
Version: 0.0.1.dev0
Summary: Utility for selecting files from a tree
Home-page: https://github.com/julianirwin/retarget
Author: Julian Irwin
Author-email: julian.irwin@gmail.com
License: MIT
Keywords: re,filesystem,utility
Platform: UNKNOWN
